Topsis_102003458_Anshika/topsis.py
Topsis_102003458_Anshika-0.2.dist-info/Licence.txt
Topsis_102003458_Anshika-0.2.dist-info/METADATA
Topsis_102003458_Anshika-0.2.dist-info/WHEEL
Topsis_102003458_Anshika-0.2.dist-info/entry_points.txt
Topsis_102003458_Anshika-0.2.dist-info/top_level.txt
Topsis_102003458_Anshika-0.2.dist-info/RECORD
