Metadata-Version: 2.1
Name: Topsis-102003458-Anshika
Version: 0.2
Summary: This is package for topsis of version 0.1
Home-page: UNKNOWN
Author: Anshika Singla
Author-email: asingla2_be20@thapar.edu
License: UNKNOWN
Platform: UNKNOWN
License-File: Licence.txt
Requires-Dist: pandas
